merlin_python_utils/__init__.py
merlin_python_utils/publisher.py
merlin_python_utils/test_publisher.py
merlin_python_utils/util.py
merlin_python_utils-0.0.2.dist-info/METADATA
merlin_python_utils-0.0.2.dist-info/RECORD
merlin_python_utils-0.0.2.dist-info/WHEEL
merlin_python_utils-0.0.2.dist-info/top_level.txt
