Metadata-Version: 2.1
Name: merlin-python-utils
Version: 0.0.2
Summary: Merlin utils
Home-page: https://http//github.com/merlinapp/merlin_python_utils
Author: Merlin Jobs inc.
Author-email: oficina@merlinjobs.com
License: UNKNOWN
Platform: UNKNOWN
Classifier: Programming Language :: Python :: 2
Classifier: License :: OSI Approved :: MIT License
Classifier: Operating System :: OS Independent
Requires-Dist: Flask (==1.0.2)
Requires-Dist: google-api-python-client (==1.7.3)
Requires-Dist: google-auth (==1.5.0)
Requires-Dist: requests (==2.18.4)
Requires-Dist: oauth2client (==4.1.2)
